[
  {
    "address": "53A Ashmount Court, Kilmainham, Dublin 8, D08TW8P",
    "askingPrice": 495000,
    "beds": 3,
    "baths": 2,
    "areaSqm": 96,
    "propertyType": "Semi-D",
    "berRating": null,
    "sourceUrl": "https://www.daft.ie/for-sale/semi-detached-house-53a-ashmount-court-kilmainham-dublin-8/6458297",
    "sourcePage": 1,
    "latitude": 53.34161675,
    "longitude": -6.299146015227763,
    "eircode": null,
    "nominatimAddress": "Millbrook Court, Kilmainham, Ushers A ED, Dublin, Dublin 8, Leinster, Éire / Ireland",
    "pricePerSqm": 5156,
    "scrapedAt": "2025-12-19T13:58:05.322Z"
  },
  {
    "address": "Apartment 20, Coultry Neighbourhood Centre, Ballymun, Dublin 9, D09ER80",
    "askingPrice": 190,
    "beds": 1,
    "baths": 1,
    "areaSqm": 90,
    "propertyType": "Apartment",
    "berRating": null,
    "sourceUrl": "https://www.daft.ie/for-sale/apartment-apartment-20-coultry-neighbourhood-centre-ballymun-dublin-9/6458242",
    "sourcePage": 1,
    "latitude": 53.3406942,
    "longitude": -6.432296057594936,
    "eircode": null,
    "nominatimAddress": "Griffeen Centre, Lucan-Esker DED 1986, Lucan, South Dublin, County Dublin, Leinster, Éire / Ireland",
    "pricePerSqm": 2,
    "scrapedAt": "2025-12-19T13:58:05.504Z"
  },
  {
    "address": "12 Beechwood Heath, Clonsilla, Dublin 15, D15PKF7",
    "askingPrice": 499000,
    "beds": 3,
    "baths": 3,
    "areaSqm": null,
    "propertyType": "Terrace",
    "berRating": null,
    "sourceUrl": "https://www.daft.ie/for-sale/house-12-beechwood-heath-clonsilla-co-dublin/6458295",
    "sourcePage": 1,
    "latitude": 53.39155985,
    "longitude": -6.447703488865155,
    "eircode": "D15 TF6F",
    "nominatimAddress": "12, Beechwood Heath, Blanchardstown-Blakestown DED 1986, Ongar, Fingal, County Dublin, Leinster, D15 TF6F, Éire / Ireland",
    "pricePerSqm": null,
    "scrapedAt": "2025-12-19T13:58:05.830Z"
  },
  {
    "address": "Apartment 18, Madison House, Rathgar, Dublin 6, D06W351",
    "askingPrice": 260000,
    "beds": 1,
    "baths": 1,
    "areaSqm": 37,
    "propertyType": "Apartment",
    "berRating": null,
    "sourceUrl": "https://www.daft.ie/for-sale/apartment-apartment-18-madison-house-rathgar-dublin-6/6458286",
    "sourcePage": 1,
    "latitude": 53.313257899999996,
    "longitude": -6.272646093405397,
    "eircode": null,
    "nominatimAddress": "Madison House, Rathgar, Rathmines West D ED, Dublin, Dublin 6, Leinster, Éire / Ireland",
    "pricePerSqm": 7027,
    "scrapedAt": "2025-12-19T13:58:05.859Z"
  },
  {
    "address": "33 Carlingford Road, Drumcondra, Dublin 9",
    "askingPrice": 675000,
    "beds": 3,
    "baths": 2,
    "areaSqm": 90,
    "propertyType": "Terrace",
    "berRating": null,
    "sourceUrl": "https://www.daft.ie/for-sale/house-33-carlingford-road-drumcondra-dublin-9/6458269",
    "sourcePage": 1,
    "latitude": 53.3666067,
    "longitude": -6.259157050540237,
    "eircode": "D09 A4P8",
    "nominatimAddress": "33, Carlingford Road, Drumcondra, Botanic B Ward 1986, Dublin, County Dublin, Leinster, D09 A4P8, Éire / Ireland",
    "pricePerSqm": 7500,
    "scrapedAt": "2025-12-19T13:58:05.882Z"
  },
  {
    "address": "Apartment 128, The Crannóg, Granitefield Manor, Rochestown Avenue, Glenageary, Co. Dublin, A96XV06",
    "askingPrice": 364950,
    "beds": 2,
    "baths": 2,
    "areaSqm": 77,
    "propertyType": "Apartment",
    "berRating": null,
    "sourceUrl": "https://www.daft.ie/for-sale/apartment-apartment-128-the-crann-g-granitefield-manor-rochestown-avenue-glenageary-co-dublin/6458187",
    "sourcePage": 1,
    "latitude": 53.28133935,
    "longitude": -6.128483777487885,
    "eircode": null,
    "nominatimAddress": "Glenageary, Dun Laoghaire-Glasthule DED 1986, Dún Laoghaire-Rathdown, County Dublin, Leinster, Éire / Ireland",
    "pricePerSqm": 4740,
    "scrapedAt": "2025-12-19T13:58:06.086Z"
  },
  {
    "address": "1 Oak Rise, Clondalkin, Dublin 22",
    "askingPrice": 425000,
    "beds": 3,
    "baths": 1,
    "areaSqm": 80,
    "propertyType": "End of Terrace",
    "berRating": null,
    "sourceUrl": "https://www.daft.ie/for-sale/house-1-oak-rise-clondalkin-dublin-22/6458246",
    "sourcePage": 1,
    "latitude": 53.312127,
    "longitude": -6.4028989,
    "eircode": "D22 F9F4",
    "nominatimAddress": "Oak Rise, Clondalkin Village DED 1986, Clondalkin, South Dublin, Dublin 22, Leinster, D22 F9F4, Éire / Ireland",
    "pricePerSqm": 5313,
    "scrapedAt": "2025-12-19T13:58:06.123Z"
  },
  {
    "address": "Laurel Cottage, Stocking Lane, Rathfarnham, Dublin 16, D16F596",
    "askingPrice": 695000,
    "beds": 2,
    "baths": 2,
    "areaSqm": 104,
    "propertyType": "Detached",
    "berRating": null,
    "sourceUrl": "https://www.daft.ie/for-sale/house-laurel-cottage-stocking-lane-rathfarnham-dublin-16/6458099",
    "sourcePage": 1,
    "latitude": 53.2865389,
    "longitude": -6.158270637927648,
    "eircode": "A96 HK30",
    "nominatimAddress": "Laurel Cottage, Lanesville, Lansville, Dun Laoghaire-Monkstown Farm DED 1986, Dún Laoghaire, Dún Laoghaire-Rathdown, County Dublin, Leinster, A96 HK30, Éire / Ireland",
    "pricePerSqm": 6683,
    "scrapedAt": "2025-12-19T13:58:06.249Z"
  },
  {
    "address": "76 Boroimhe Hawthorns, Swords, Co., Dublin",
    "askingPrice": 425000,
    "beds": 3,
    "baths": 2,
    "areaSqm": 85,
    "propertyType": "End of Terrace",
    "berRating": null,
    "sourceUrl": "https://www.daft.ie/for-sale/house-76-boroimhe-hawthorns-swords-co-dublin/6458204",
    "sourcePage": 1,
    "latitude": 53.4467752,
    "longitude": -6.2360635,
    "eircode": "K67 K336",
    "nominatimAddress": "Boroimhe Hawthorns, Boroimhe, Swords-Forrest DED 1986, Swords, Fingal, County Dublin, Leinster, K67 K336, Éire / Ireland",
    "pricePerSqm": 5000,
    "scrapedAt": "2025-12-19T13:58:06.272Z"
  },
  {
    "address": "243 Premier Square, Finglas, Dublin 11",
    "askingPrice": 295000,
    "beds": 2,
    "baths": 2,
    "areaSqm": 70,
    "propertyType": "Apartment",
    "berRating": null,
    "sourceUrl": "https://www.daft.ie/for-sale/property-243-premier-square-finglas-dublin-11/6458133",
    "sourcePage": 1,
    "latitude": 53.3811593,
    "longitude": -6.288533,
    "eircode": "D11 VNW2",
    "nominatimAddress": "Premier Square, Finglas, Ballygall A Ward 1986, Dublin, Dublin 11, Leinster, D11 VNW2, Éire / Ireland",
    "pricePerSqm": 4214,
    "scrapedAt": "2025-12-19T13:58:06.297Z"
  },
  {
    "address": "7 Beresford House, Custom House Square, I.F.S.C, Co., Dublin",
    "askingPrice": 395000,
    "beds": 2,
    "baths": 1,
    "areaSqm": 52,
    "propertyType": "Apartment",
    "berRating": "E",
    "sourceUrl": "https://www.daft.ie/for-sale/property-7-beresford-house-custom-house-square-i-f-s-c-co-dublin/6458132",
    "sourcePage": 1,
    "latitude": 53.3495091,
    "longitude": -6.243892922386998,
    "eircode": "D01 T8Y1",
    "nominatimAddress": "Beresford House, Mayor Street Lower, IFSC II, North Dock C Ward 1986, Dublin, County Dublin, Leinster, D01 T8Y1, Éire / Ireland",
    "pricePerSqm": 7596,
    "scrapedAt": "2025-12-19T13:58:06.471Z"
  },
  {
    "address": "49 Barons Hall Park, Balbriggan, Co., Dublin",
    "askingPrice": 235000,
    "beds": 2,
    "baths": 1,
    "areaSqm": 64,
    "propertyType": "Apartment",
    "berRating": null,
    "sourceUrl": "https://www.daft.ie/for-sale/property-49-barons-hall-park-balbriggan-co-dublin/6458103",
    "sourcePage": 1,
    "latitude": 53.609832,
    "longitude": -6.1861964,
    "eircode": null,
    "nominatimAddress": "Balbriggan, Fingal, County Dublin, Leinster, Éire / Ireland",
    "pricePerSqm": 3672,
    "scrapedAt": "2025-12-19T13:58:06.814Z"
  },
  {
    "address": "7 Rathborne Dale, Rathborne Park, Ashtown, Dublin 15, D15KPF9",
    "askingPrice": 649000,
    "beds": 4,
    "baths": 3,
    "areaSqm": 128,
    "propertyType": "End of Terrace",
    "berRating": null,
    "sourceUrl": "https://www.daft.ie/for-sale/house-7-rathborne-dale-rathborne-park-ashtown-dublin-15/6319825",
    "sourcePage": 1,
    "latitude": 53.376568,
    "longitude": -6.3204086,
    "eircode": "D15 X63X",
    "nominatimAddress": "Rathborne Park, Ashtown A Ward 1986, Dublin, Dublin 11, Leinster, D15 X63X, Éire / Ireland",
    "pricePerSqm": 5070,
    "scrapedAt": "2025-12-19T13:58:07.168Z"
  },
  {
    "address": "340 Block 21a, Marina Village, Malahide, Co. Dublin, K36XY01",
    "askingPrice": 495000,
    "beds": 2,
    "baths": 2,
    "areaSqm": 67,
    "propertyType": "Apartment",
    "berRating": null,
    "sourceUrl": "https://www.daft.ie/for-sale/property-340-block-21a-marina-village-malahide-co-dublin/6458054",
    "sourcePage": 1,
    "latitude": 53.45396715,
    "longitude": -6.154726479691635,
    "eircode": null,
    "nominatimAddress": "Marina Village, Malahide East DED 1986, Malahide, Fingal, County Dublin, Leinster, Éire / Ireland",
    "pricePerSqm": 7388,
    "scrapedAt": "2025-12-19T13:58:07.366Z"
  },
  {
    "address": "56 Wilson Road, Mount, Merrion, Blackrock, Co. Dublin, A94YW8K",
    "askingPrice": 1675000,
    "beds": 4,
    "baths": 4,
    "areaSqm": 201,
    "propertyType": "Semi-D",
    "berRating": null,
    "sourceUrl": "https://www.daft.ie/for-sale/house-56-wilson-road-mount-merrion-blackrock-co-dublin/6458051",
    "sourcePage": 1,
    "latitude": 53.29714405,
    "longitude": -6.21208795,
    "eircode": "A94 EK75",
    "nominatimAddress": "56, Wilson Road, Mount Merrion, Stillorgan-Deerpark DED 1986, Dundrum, Dún Laoghaire-Rathdown, County Dublin, Leinster, A94 EK75, Éire / Ireland",
    "pricePerSqm": 8333,
    "scrapedAt": "2025-12-19T13:58:07.394Z"
  },
  {
    "address": "1 Saint Killian'S Park, Dublin 22, Clondalkin, Dublin 22, D22HE03",
    "askingPrice": 349950,
    "beds": 3,
    "baths": 1,
    "areaSqm": 86,
    "propertyType": "Terrace",
    "berRating": null,
    "sourceUrl": "https://www.daft.ie/for-sale/house-1-saint-killians-park-dublin-22-clondalkin-co-dublin/6457834",
    "sourcePage": 1,
    "latitude": 53.3236501,
    "longitude": -6.3908046,
    "eircode": "D22 K0T3",
    "nominatimAddress": "Saint Killian's Park, Clondalkin-Monastery DED 1986, Clondalkin, South Dublin, Dublin 22, Leinster, D22 K0T3, Éire / Ireland",
    "pricePerSqm": 4069,
    "scrapedAt": "2025-12-19T13:58:07.431Z"
  },
  {
    "address": "Apartment 38, Tramway Court, Kilnamanagh, Dublin 24, D24NX92",
    "askingPrice": 260000,
    "beds": 2,
    "baths": 2,
    "areaSqm": 68,
    "propertyType": "Apartment",
    "berRating": null,
    "sourceUrl": "https://www.daft.ie/for-sale/apartment-apartment-38-tramway-court-kilnamanagh-dublin-24/6457809",
    "sourcePage": 1,
    "latitude": 53.28997885,
    "longitude": -6.36495369373608,
    "eircode": "D24 T294",
    "nominatimAddress": "Tramway Court, Tallaght-Kingswood DED 1986, Tallaght, South Dublin, Dublin 24, Leinster, D24 T294, Éire / Ireland",
    "pricePerSqm": 3824,
    "scrapedAt": "2025-12-19T13:58:07.567Z"
  },
  {
    "address": "19 Ballyowen Hall, Ballyowen Lane, Lucan, Co. Dublin, K78EC80",
    "askingPrice": 305000,
    "beds": 2,
    "baths": 2,
    "areaSqm": 60,
    "propertyType": "Apartment",
    "berRating": null,
    "sourceUrl": "https://www.daft.ie/for-sale/property-19-ballyowen-hall-ballyowen-lane-lucan-co-dublin/6457801",
    "sourcePage": 1,
    "latitude": 53.3533359,
    "longitude": -6.4166383,
    "eircode": "K78 Y9W0",
    "nominatimAddress": "Ballyowen Hall, Lucan-Esker DED 1986, Lucan, South Dublin, County Dublin, Leinster, K78 Y9W0, Éire / Ireland",
    "pricePerSqm": 5083,
    "scrapedAt": "2025-12-19T13:58:07.637Z"
  }
]